{
    "name": "random-3-12751",
    "comment": "size=3 seed=12751",
    "nodes": ["+0", "-0", "+1", "-1", "+2", "-2", "+3", "-3"],
    "precedence": {
        "+0": "-0",
        "+1": "-1",
        "+2": "-2",
        "+3": "-3"
    },
    "edges": [
        [    0,    0,  572,  935,  648,  572,  485,  577],
        [    0,    0,  572,  935,  648,  572,  485,  577],
        [  572,  572,    0,  777,  149,  422,  404,  500],
        [  935,  935,  777,    0,  651,  398,  472,  363],
        [  648,  648,  149,  651,    0,  338,  350,  421],
        [  572,  572,  422,  398,  338,    0,   88,   84],
        [  485,  485,  404,  472,  350,   88,    0,  116],
        [  577,  577,  500,  363,  421,   84,  116,    0]
    ]
}
