{
    "name": "random-4-5530",
    "comment": "size=4 seed=5530",
    "nodes": ["+0", "-0", "+1", "-1", "+2", "-2", "+3", "-3", "+4", "-4"],
    "precedence": {
        "+0": "-0",
        "+1": "-1",
        "+2": "-2",
        "+3": "-3",
        "+4": "-4"
    },
    "edges": [
        [    0,    0,  337,  618,  839,  368,  119,  471,  582,  151],
        [    0,    0,  337,  618,  839,  368,  119,  471,  582,  151],
        [  337,  337,    0,  768,  810,  280,  396,  639,  554,  430],
        [  618,  618,  768,    0,  431,  518,  719,  148,  362,  475],
        [  839,  839,  810,  431,    0,  538,  957,  491,  265,  740],
        [  368,  368,  280,  518,  538,    0,  479,  410,  277,  352],
        [  119,  119,  396,  719,  957,  479,    0,  572,  700,  245],
        [  471,  471,  639,  148,  491,  410,  572,    0,  335,  328],
        [  582,  582,  554,  362,  265,  277,  700,  335,    0,  499],
        [  151,  151,  430,  475,  740,  352,  245,  328,  499,    0]
    ]
}
