{
    "name": "random-55-13609",
    "comment": "size=55 seed=13609",
    "nodes": ["+0", "-0", "+1", "-1", "+2", "-2", "+3", "-3", "+4", "-4", "+5", "-5", "+6", "-6", "+7", "-7", "+8", "-8", "+9", "-9", "+10", "-10", "+11", "-11", "+12", "-12", "+13", "-13", "+14", "-14", "+15", "-15", "+16", "-16", "+17", "-17", "+18", "-18", "+19", "-19", "+20", "-20", "+21", "-21", "+22", "-22", "+23", "-23", "+24", "-24", "+25", "-25", "+26", "-26", "+27", "-27", "+28", "-28", "+29", "-29", "+30", "-30", "+31", "-31", "+32", "-32", "+33", "-33", "+34", "-34", "+35", "-35", "+36", "-36", "+37", "-37", "+38", "-38", "+39", "-39", "+40", "-40", "+41", "-41", "+42", "-42", "+43", "-43", "+44", "-44", "+45", "-45", "+46", "-46", "+47", "-47", "+48", "-48", "+49", "-49", "+50", "-50", "+51", "-51", "+52", "-52", "+53", "-53", "+54", "-54", "+55", "-55"],
    "precedence": {
        "+0": "-0",
        "+1": "-1",
        "+2": "-2",
        "+3": "-3",
        "+4": "-4",
        "+5": "-5",
        "+6": "-6",
        "+7": "-7",
        "+8": "-8",
        "+9": "-9",
        "+10": "-10",
        "+11": "-11",
        "+12": "-12",
        "+13": "-13",
        "+14": "-14",
        "+15": "-15",
        "+16": "-16",
        "+17": "-17",
        "+18": "-18",
        "+19": "-19",
        "+20": "-20",
        "+21": "-21",
        "+22": "-22",
        "+23": "-23",
        "+24": "-24",
        "+25": "-25",
        "+26": "-26",
        "+27": "-27",
        "+28": "-28",
        "+29": "-29",
        "+30": "-30",
        "+31": "-31",
        "+32": "-32",
        "+33": "-33",
        "+34": "-34",
        "+35": "-35",
        "+36": "-36",
        "+37": "-37",
        "+38": "-38",
        "+39": "-39",
        "+40": "-40",
        "+41": "-41",
        "+42": "-42",
        "+43": "-43",
        "+44": "-44",
        "+45": "-45",
        "+46": "-46",
        "+47": "-47",
        "+48": "-48",
        "+49": "-49",
        "+50": "-50",
        "+51": "-51",
        "+52": "-52",
        "+53": "-53",
        "+54": "-54",
        "+55": "-55"
    },
    "edges": [
        [    0,    0,  318,  321,  485,  198,  114,  348,  405,  311,  643,  442,  481,  453,  252,  456,  242,  514,  439,  249,  326,  285,  507,  535,  498,  562,  339,  475,  285,  289,  220,  482,  185,  507,  461,  365,  321,  202,  314,  583,  127,  514,  405,  390,  568,  316,  333,   90,  346,  307,  382,  514,  511,  357,  427,  327,  358,  190,  603,  503,  502,  586,  378,  546,  349,  284,  519,  145,  473,  170,  516,  506,  175,  641,  326,  333,  302,  457,  401,  333,  279,  238,  267,  583,  507,  347,  267,  454,  190,  423,  380,  428,  380,  324,  393,  407,  259,  137,  631,  361,  435,  429,  432,  616,  377,  567,  275,  363,  307,  489,  334,  242],
        [    0,    0,    0,    0,    0,    0,    0,    0,    0,    0,    0,    0,    0,    0,    0,    0,    0,    0,    0,    0,    0,    0,    0,    0,    0,    0,    0,    0,    0,    0,    0,    0,    0,    0,    0,    0,    0,    0,    0,    0,    0,    0,    0,    0,    0,    0,    0,    0,    0,    0,    0,    0,    0,    0,    0,    0,    0,    0,    0,    0,    0,    0,    0,    0,    0,    0,    0,    0,    0,    0,    0,    0,    0,    0,    0,    0,    0,    0,    0,    0,    0,    0,    0,    0,    0,    0,    0,    0,    0,    0,    0,    0,    0,    0,    0,    0,    0,    0,    0,    0,    0,    0,    0,    0,    0,    0,    0,    0,    0,    0,    0,    0],
        [  318,    0,    0,  629,  803,  435,  369,  525,  687,  578,  348,  548,  217,  497,  360,  595,  255,  829,  437,  527,  286,  365,  810,  272,  811,  244,  546,  721,  393,  593,  151,  761,  135,  445,  227,  384,  598,  455,  589,  345,  233,  361,  675,  618,  749,   64,  626,  229,  557,  137,  699,  524,  235,  422,  730,  389,  443,  442,  746,  200,  342,  288,  241,  863,  242,  251,  681,  324,  160,  473,  618,  350,  262,  609,  490,  375,  615,  431,  119,  626,  577,  323,  529,  777,  272,  137,  299,  318,  503,  737,  696,  719,  266,   18,   76,  696,  479,  344,  324,  136,  749,  739,  145,  628,  628,  529,  524,  219,  463,  184,  528,  460],
        [  321,    0,  629,    0,  227,  233,  266,  500,  132,  143,  963,  440,  802,  682,  380,  408,  456,  289,  547,  309,  520,  541,  187,  856,  186,  871,  263,  478,  524,  238,  501,  408,  495,  643,  781,  628,  328,  348,  332,  901,  443,  819,  383,  457,  644,  612,  287,  404,  458,  579,  112,  752,  785,  447,  296,  439,  585,  215,  716,  821,  709,  906,  606,  254,  572,  587,  630,  329,  774,  249,  688,  812,  476,  714,  324,  593,   36,  723,  690,   63,   64,  400,  161,  639,  758,  668,  552,  657,  134,  225,  192,  339,  687,  631,  704,  336,  410,  393,  948,  682,  234,  259,  719,  654,  188,  663,  185,  677,  498,  784,  284,  405],
        [  485,    0,  803,  227,    0,  453,  467,  512,  306,  365, 1115,  663,  946,  718,  602,  625,  667,   75,  773,  341,  737,  617,  213,  995,  126, 1046,  486,  391,  591,  246,  693,  285,  670,  868,  916,  699,  309,  412,  319, 1027,  587,  920,  311,  423,  574,  798,  254,  574,  456,  777,  118,  788,  985,  673,  177,  664,  633,  434,  662,  981,  928, 1061,  819,   86,  785,  700,  587,  537,  958,  344,  680,  915,  598,  939,  550,  665,  217,  786,  881,  279,  289,  618,  387,  556,  966,  812,  651,  875,  310,   94,  120,  234,  798,  809,  877,  248,  449,  502, 1109,  827,   87,  126,  912,  876,  395,  889,  412,  800,  538,  972,  508,  454],
        [  198,    0,  435,  233,  453,    0,   86,  519,  254,  144,  782,  270,  635,  648,  149,  269,  227,  507,  329,  367,  287,  481,  391,  691,  415,  668,  142,  591,  479,  355,  291,  560,  310,  420,  625,  562,  424,  355,  422,  750,  314,  700,  503,  530,  720,  405,  410,  241,  501,  360,  336,  711,  561,  230,  470,  214,  551,   22,  770,  635,  477,  722,  375,  486,  340,  476,  683,  113,  565,  273,  699,  691,  371,  515,  142,  530,  237,  654,  475,  206,  170,  167,   95,  728,  528,  508,  463,  424,  168,  427,  385,  494,  567,  434,  508,  481,  423,  328,  758,  519,  438,  450,  503,  470,  195,  454,   90,  543,  489,  569,  139,  409],
        [  114,    0,  369,  266,  467,   86,    0,  448,  320,  215,  712,  335,  559,  566,  166,  344,  201,  511,  358,  314,  278,  398,  442,  615,  451,  609,  226,  543,  397,  323,  235,  529,  238,  439,  546,  478,  379,  289,  376,  671,  230,  617,  462,  472,  658,  348,  376,  159,  437,  314,  353,  628,  521,  266,  452,  241,  470,   81,  702,  566,  468,  653,  353,  513,  319,  391,  616,   72,  510,  222,  624,  608,  286,  556,  214,  446,  259,  569,  425,  257,  210,  166,  167,  670,  499,  430,  378,  416,  159,  424,  381,  466,  483,  370,  444,  450,  354,  248,  692,  442,  436,  441,  454,  521,  275,  487,  170,  460,  413,  518,  221,  339],
        [  348,    0,  525,  500,  512,  519,  448,    0,  627,  578,  723,  782,  558,  207,  600,  787,  577,  489,  784,  193,  660,  173,  655,  591,  600,  723,  652,  222,  140,  280,  515,  308,  444,  847,  513,  221,  203,  166,  194,  593,  317,  455,  228,  119,  230,  562,  258,  386,   60,  592,  475,  277,  759,  704,  352,  674,  138,  503,  256,  626,  814,  683,  688,  597,  666,  299,  172,  492,  675,  262,  190,  454,  267,  987,  659,  198,  465,  290,  641,  548,  501,  585,  550,  254,  784,  450,  239,  771,  400,  418,  399,  306,  367,  540,  578,  283,   97,  219,  739,  466,  427,  393,  669,  963,  647,  911,  569,  394,   64,  704,  655,  110],
        [  405,    0,  687,  132,  306,  254,  320,  627,    0,  112, 1031,  375,  878,  803,  381,  328,  476,  379,  513,  438,  523,  654,  152,  933,  211,  922,  207,  607,  640,  370,  545,  532,  557,  610,  862,  741,  459,  471,  463,  986,  531,  917,  513,  588,  775,  659,  418,  475,  588,  613,  215,  873,  811,  418,  416,  420,  705,  245,  847,  885,  703,  972,  617,  297,  583,  685,  761,  366,  819,  371,  816,  910,  574,  653,  283,  706,  167,  836,  729,   81,  133,  409,  160,  770,  771,  746,  657,  652,  239,  336,  311,  464,  784,  686,  760,  463,  535,  501, 1010,  759,  342,  373,  756,  583,   98,  614,  171,  768,  622,  823,  234,  529],
        [  311,    0,  578,  143,  365,  144,  215,  578,  112,    0,  924,  299,  773,  736,  271,  266,  364,  431,  416,  398,  413,  579,  257,  829,  297,  811,  121,  597,  569,  351,  434,  540,  450,  513,  760,  664,  436,  414,  438,  885,  437,  825,  503,  559,  751,  548,  405,  373,  547,  501,  254,  804,  699,  318,  433,  316,  638,  137,  814,  777,  597,  864,  507,  378,  472,  595,  727,  256,  708,  316,  766,  817,  485,  574,  188,  630,  166,  759,  617,   87,   93,  298,   49,  751,  661,  644,  573,  545,  179,  367,  332,  471,  691,  576,  651,  464,  482,  423,  901,  656,  376,  399,  644,  512,   70,  527,   60,  671,  562,  711,  144,  472],
        [  643,    0,  348,  963, 1115,  782,  712,  723, 1031,  924,    0,  878,  171,  591,  703,  930,  595, 1128,  741,  800,  604,  552, 1148,  132, 1141,  171,  893,  943,  586,  883,  498, 1013,  475,  715,  211,  511,  862,  723,  852,  162,  529,  310,  926,  838,  906,  390,  903,  561,  773,  457, 1021,  573,  368,  751, 1012,  721,  596,  788,  868,  149,  568,   61,  527, 1183,  545,  434,  831,  671,  266,  772,  727,  304,  521,  871,  835,  527,  945,  488,  354,  967,  916,  666,  875,  942,  448,  304,  493,  574,  833, 1038, 1000,  987,  356,  353,  280,  962,  718,  618,   60,  288, 1050, 1032,  343,  913,  976,  800,  872,  332,  663,  290,  874,  704],
        [  442,    0,  548,  440,  663,  270,  335,  782,  375,  299,  878,    0,  765,  890,  206,   65,  296,  729,  171,  636,  275,  721,  524,  819,  584,  728,  178,  858,  725,  618,  406,  820,  467,  260,  772,  793,  692,  622,  691,  893,  531,  883,  769,  799,  988,  493,  674,  444,  769,  422,  552,  947,  561,  128,  721,  160,  798,  289, 1036,  734,  394,  819,  362,  668,  337,  683,  949,  302,  620,  543,  957,  873,  595,  279,  129,  764,  461,  878,  527,  385,  384,  237,  286,  997,  497,  664,  688,  353,  429,  662,  625,  752,  759,  538,  603,  742,  688,  578,  838,  670,  672,  692,  544,  214,  277,  244,  260,  723,  747,  608,  157,  673],
        [  481,    0,  217,  802,  946,  635,  559,  558,  878,  773,  171,  765,    0,  446,  574,  811,  472,  958,  649,  629,  500,  386,  988,   57,  976,  196,  755,  776,  419,  713,  365,  844,  325,  643,   51,  354,  692,  552,  682,  130,  363,  200,  756,  671,  752,  275,  732,  403,  606,  349,  854,  442,  343,  639,  841,  606,  436,  638,  722,   90,  516,  125,  441, 1016,  450,  265,  678,  526,  221,  603,  582,  190,  351,  807,  704,  365,  782,  350,  275,  810,  758,  538,  725,  787,  412,  136,  324,  507,  670,  868,  831,  817,  196,  228,  173,  792,  548,  447,  182,  121,  880,  862,  279,  835,  830,  729,  724,  164,  497,  257,  739,  534],
        [  453,    0,  497,  682,  718,  648,  566,  207,  803,  736,  591,  890,  446,    0,  690,  908,  636,  696,  854,  386,  710,  170,  849,  464,  800,  636,  788,  405,  170,  480,  546,  507,  468,  897,  396,  114,  409,  335,  400,  441,  365,  290,  432,  316,  320,  551,  464,  451,  266,  603,  673,   72,  724,  791,  558,  758,   99,  636,  278,  530,  829,  564,  711,  802,  697,  248,  246,  589,  619,  434,  137,  293,  300, 1052,  778,  132,  649,  106,  614,  723,  672,  666,  701,  358,  768,  381,  214,  795,  566,  624,  603,  512,  256,  514,  526,  489,  277,  320,  621,  392,  633,  599,  636, 1044,  806,  972,  715,  300,  186,  653,  786,  278],
        [  252,    0,  360,  380,  602,  149,  166,  600,  381,  271,  703,  206,  574,  690,    0,  241,  108,  655,  193,  479,  143,  521,  527,  630,  559,  568,  198,  708,  528,  486,  210,  692,  264,  277,  576,  590,  544,  448,  541,  699,  328,  680,  627,  634,  817,  313,  539,  241,  595,  251,  485,  745,  434,  105,  610,   77,  600,  169,  855,  555,  330,  642,  237,  633,  203,  478,  771,  108,  460,  387,  766,  670,  392,  392,  132,  562,  385,  673,  366,  347,  317,   37,  229,  831,  391,  464,  484,  277,  309,  573,  530,  629,  554,  352,  423,  613,  510,  386,  670,  472,  584,  594,  390,  364,  299,  322,  212,  519,  558,  457,  175,  493],
        [  456,    0,  595,  408,  625,  269,  344,  787,  328,  266,  930,   65,  811,  908,  241,    0,  340,  694,  235,  630,  330,  739,  473,  866,  538,  784,  150,  847,  740,  603,  448,  801,  504,  324,  815,  815,  682,  624,  681,  937,  555,  920,  756,  794,  986,  543,  659,  470,  769,  473,  518,  968,  622,  182,  697,  210,  813,  286, 1038,  785,  457,  871,  420,  624,  394,  712,  951,  324,  675,  539,  967,  910,  618,  329,  131,  785,  432,  903,  581,  349,  356,  275,  263,  992,  559,  704,  711,  416,  416,  632,  597,  732,  792,  586,  653,  723,  692,  591,  892,  711,  641,  665,  600,  255,  232,  302,  238,  759,  756,  665,  137,  678],
        [  242,    0,  255,  456,  667,  227,  201,  577,  476,  364,  595,  296,  472,  636,  108,  340,    0,  712,  218,  488,   85,  470,  617,  526,  640,  461,  304,  716,  483,  516,  111,  717,  178,  271,  477,  529,  559,  442,  553,  598,  274,  591,  643,  631,  803,  206,  565,  192,  583,  143,  551,  684,  335,  172,  649,  138,  553,  242,  829,  448,  268,  535,  152,  708,  119,  406,  749,  131,  353,  403,  726,  580,  338,  417,  240,  505,  454,  605,  259,  432,  394,   73,  318,  821,  302,  369,  423,  217,  360,  625,  582,  658,  471,  247,  316,  640,  496,  358,  562,  375,  637,  641,  284,  411,  401,  339,  306,  432,  527,  352,  283,  478],
        [  514,    0,  829,  289,   75,  507,  511,  489,  379,  431, 1128,  729,  958,  696,  655,  694,  712,    0,  832,  336,  786,  611,  287, 1005,  199, 1070,  551,  341,  582,  246,  729,  229,  698,  925,  925,  688,  290,  412,  300, 1031,  605,  916,  272,  389,  523,  830,  238,  603,  430,  814,  178,  765, 1021,  731,  138,  720,  617,  487,  613,  999,  977, 1076,  863,  139,  830,  704,  544,  582,  986,  359,  645,  912,  608, 1003,  612,  657,  274,  772,  914,  346,  349,  668,  449,  502, 1008,  826,  652,  924,  353,   92,  134,  190,  800,  836,  902,  210,  438,  511, 1126,  842,   80,  100,  945,  942,  465,  951,  474,  807,  522, 1003,  573,  446],
        [  439,    0,  437,  547,  773,  329,  358,  784,  513,  416,  741,  171,  649,  854,  193,  235,  218,  832,    0,  672,  154,  687,  664,  700,  713,  582,  306,  901,  699,  678,  318,  884,  393,   98,  664,  747,  737,  638,  733,  778,  490,  793,  820,  825, 1006,  376,  731,  407,  784,  302,  657,  902,  402,  101,  798,  118,  770,  350, 1039,  604,  224,  684,  215,  793,  200,  622,  956,  298,  476,  579,  941,  782,  555,  203,  230,  723,  559,  822,  388,  502,  485,  201,  387, 1021,  332,  567,  641,  187,  496,  755,  713,  819,  680,  424,  479,  804,  698,  567,  696,  570,  766,  779,  399,  195,  417,  129,  364,  638,  738,  459,  279,  680],
        [  249,    0,  527,  309,  341,  367,  314,  193,  438,  398,  800,  636,  629,  386,  479,  630,  488,  336,  672,    0,  573,  277,  465,  674,  414,  758,  486,  230,  250,   96,  462,  238,  410,  749,  593,  358,   74,   78,   66,  697,  294,  581,  157,  165,  356,  543,  104,  323,  151,  549,  287,  458,  744,  580,  212,  555,  296,  348,  417,  678,  751,  750,  626,  422,  597,  370,  329,  376,  687,   94,  380,  577,  281,  870,  508,  325,  274,  447,  629,  360,  315,  474,  377,  362,  749,  500,  317,  702,  221,  251,  222,  193,  465,  537,  595,  170,  111,  187,  802,  516,  262,  237,  659,  833,  466,  800,  399,  473,  202,  709,  494,  114],
        [  326,    0,  286,  520,  737,  287,  278,  660,  523,  413,  604,  275,  500,  710,  143,  330,   85,  786,  154,  573,    0,  547,  670,  552,  701,  454,  333,  800,  562,  597,  167,  800,  243,  189,  512,  600,  643,  527,  637,  629,  352,  640,  727,  715,  886,  226,  647,  274,  667,  152,  620,  755,  299,  149,  729,  123,  630,  305,  911,  462,  191,  545,   97,  773,   65,  473,  831,  207,  346,  486,  805,  629,  415,  343,  259,  579,  522,  672,  252,  489,  457,  120,  371,  905,  250,  414,  496,  139,  435,  701,  658,  740,  527,  273,  332,  722,  580,  441,  564,  417,  713,  718,  270,  348,  439,  263,  354,  485,  608,  336,  308,  562],
        [  285,    0,  365,  541,  617,  481,  398,  173,  654,  579,  552,  721,  386,  170,  521,  739,  470,  611,  687,  277,  547,    0,  719,  421,  680,  551,  622,  391,   34,  372,  387,  465,  310,  735,  342,   88,  326,  207,  315,  430,  197,  305,  378,  286,  385,  410,  375,  283,  221,  452,  551,  230,  600,  622,  481,  589,   84,  471,  382,  453,  679,  511,  557,  698,  540,  127,  316,  420,  508,  295,  261,  302,  133,  887,  609,   53,  511,  183,  484,  575,  522,  497,  540,  416,  633,  278,   68,  641,  416,  528,  498,  447,  199,  382,  412,  423,  176,  157,  567,  294,  539,  512,  510,  877,  648,  808,  553,  222,  112,  539,  619,  166],
        [  507,    0,  810,  187,  213,  391,  442,  655,  152,  257, 1148,  524,  988,  849,  527,  473,  617,  287,  664,  465,  670,  719,    0, 1041,   88, 1050,  359,  582,  699,  377,  675,  486,  676,  762,  967,  805,  463,  518,  470, 1087,  629, 1003,  493,  590,  762,  789,  411,  588,  606,  749,  183,  921,  951,  569,  370,  571,  756,  378,  844, 1004,  853, 1090,  762,  169,  728,  772,  763,  499,  951,  424,  838,  997,  661,  801,  435,  770,  211,  899,  863,  187,  233,  553,  300,  749,  916,  853,  735,  802,  320,  280,  274,  426,  872,  811,  885,  433,  573,  576, 1131,  867,  280,  320,  892,  728,  249,  765,  316,  863,  664,  957,  385,  572],
        [  535,    0,  272,  856,  995,  691,  615,  591,  933,  829,  132,  819,   57,  464,  630,  866,  526, 1005,  700,  674,  552,  421, 1041,    0, 1028,  207,  811,  812,  455,  760,  420,  884,  381,  691,   82,  380,  735,  597,  725,   82,  415,  193,  796,  707,  776,  327,  777,  458,  642,  401,  906,  451,  376,  693,  886,  660,  465,  693,  741,  113,  558,  103,  490, 1067,  501,  306,  701,  582,  256,  652,  600,  185,  399,  853,  760,  396,  835,  362,  320,  864,  812,  594,  781,  812,  450,  189,  364,  552,  723,  916,  879,  859,  225,  282,  222,  835,  589,  495,  159,  175,  928,  908,  320,  884,  886,  777,  780,  203,  532,  289,  795,  575],
        [  498,    0,  811,  186,  126,  415,  451,  600,  211,  297, 1141,  584,  976,  800,  559,  538,  640,  199,  713,  414,  701,  680,   88, 1028,    0, 1054,  412,  506,  658,  321,  686,  405,  677,  810,  951,  766,  400,  475,  408, 1069,  614,  974,  420,  524,  688,  797,  346,  584,  547,  765,  129,  871,  971,  615,  292,  612,  709,  399,  773, 1000,  888, 1084,  790,   87,  755,  746,  695,  515,  959,  389,  777,  968,  637,  862,  483,  731,  197,  857,  876,  214,  246,  582,  332,  673,  942,  841,  704,  836,  309,  202,  205,  348,  846,  814,  887,  358,  524,  547, 1128,  856,  200,  240,  905,  793,  308,  821,  353,  842,  615,  969,  437,  525],
        [  562,    0,  244,  871, 1046,  668,  609,  723,  922,  811,  171,  728,  196,  636,  568,  784,  461, 1070,  582,  758,  454,  551, 1050,  207, 1054,    0,  764,  934,  583,  831,  377,  987,  379,  548,  245,  535,  827,  683,  818,  281,  467,  394,  900,  829,  930,  264,  860,  473,  764,  318,  943,  637,  198,  602,  966,  575,  613,  677,  909,  107,  399,  128,  369, 1107,  392,  425,  857,  556,  109,  712,  770,  384,  480,  703,  699,  541,  858,  543,  204,  865,  818,  533,  763,  963,  278,  273,  484,  408,  747,  978,  937,  951,  380,  240,  169,  927,  695,  572,  118,  258,  991,  979,  185,  748,  856,  632,  755,  339,  660,  123,  743,  678],
        [  339,    0,  546,  263,  486,  142,  226,  652,  207,  121,  893,  178,  755,  788,  198,  150,  304,  551,  306,  486,  333,  622,  359,  811,  412,  764,    0,  699,  619,  455,  396,  652,  432,  403,  750,  703,  534,  487,  534,  875,  454,  836,  607,  650,  842,  505,  510,  376,  629,  447,  375,  852,  630,  212,  548,  219,  691,  153,  898,  745,  503,  833,  429,  494,  396,  615,  811,  232,  657,  396,  836,  827,  511,  454,   78,  671,  285,  795,  563,  207,  208,  232,  114,  847,  581,  635,  604,  454,  268,  486,  450,  583,  704,  541,  614,  574,  555,  469,  863,  645,  495,  517,  587,  391,  112,  410,   90,  676,  626,  655,   27,  543],
        [  475,    0,  721,  478,  391,  591,  543,  222,  607,  597,  943,  858,  776,  405,  708,  847,  716,  341,  901,  230,  800,  391,  582,  812,  506,  934,  699,    0,  358,  246,  680,  116,  619,  978,  732,  441,  167,  278,  169,  814,  494,  674,   95,  106,  184,  748,  193,  541,  171,  764,  406,  467,  949,  809,  215,  784,  356,  571,  273,  841,  974,  901,  848,  474,  821,  514,  207,  605,  877,  322,  320,  674,  460, 1099,  730,  419,  444,  501,  831,  539,  507,  704,  586,  168,  963,  663,  454,  926,  432,  305,  309,  158,  588,  734,  781,  149,  243,  382,  957,  678,  307,  267,  861, 1060,  658, 1030,  610,  612,  280,  904,  711,  261],
        [  285,    0,  393,  524,  591,  479,  397,  140,  640,  569,  586,  725,  419,  170,  528,  740,  483,  582,  699,  250,  562,   34,  699,  455,  658,  583,  619,  358,    0,  346,  405,  432,  329,  751,  375,  109,  295,  183,  285,  463,  211,  335,  346,  253,  356,  435,  345,  293,  188,  474,  529,  235,  628,  630,  451,  598,   74,  467,  358,  486,  700,  544,  577,  672,  559,  159,  288,  424,  539,  276,  244,  332,  149,  900,  610,   75,  493,  201,  511,  561,  508,  506,  532,  386,  658,  311,  100,  661,  402,  501,  472,  416,  232,  409,  442,  391,  145,  151,  600,  326,  511,  483,  538,  887,  639,  822,  546,  255,   78,  569,  617,  138],
        [  289,    0,  593,  238,  246,  355,  323,  280,  370,  351,  883,  618,  713,  480,  486,  603,  516,  246,  678,   96,  597,  372,  377,  760,  321,  831,  455,  246,  346,    0,  509,  207,  468,  762,  679,  454,   90,  168,   95,  787,  364,  675,  153,  220,  406,  601,   56,  375,  230,  596,  196,  551,  799,  581,  139,  560,  391,  334,  479,  756,  783,  832,  662,  327,  631,  459,  394,  392,  752,  122,  462,  670,  362,  869,  490,  420,  203,  542,  687,  297,  261,  489,  341,  403,  795,  581,  408,  732,  190,  158,  127,  143,  556,  602,  665,  127,  205,  266,  882,  597,  170,  150,  718,  824,  414,  805,  366,  561,  296,  772,  467,  209],
        [  220,    0,  151,  501,  693,  291,  235,  515,  545,  434,  498,  406,  365,  546,  210,  448,  111,  729,  318,  462,  167,  387,  675,  420,  686,  377,  396,  680,  405,  509,    0,  699,   78,  351,  367,  436,  535,  403,  528,  490,  199,  481,  618,  586,  744,  114,  552,  140,  532,   88,  582,  589,  293,  282,  647,  248,  471,  300,  760,  349,  300,  437,  174,  745,  154,  307,  684,  179,  276,  389,  648,  471,  257,  509,  340,  415,  491,  506,  190,  490,  444,  174,  386,  766,  288,  259,  333,  257,  385,  638,  595,  647,  364,  146,  219,  626,  445,  302,  469,  265,  651,  647,  220,  512,  482,  429,  379,  323,  459,  284,  378,  427],
        [  482,    0,  761,  408,  285,  560,  529,  308,  532,  540, 1013,  820,  844,  507,  692,  801,  717,  229,  884,  238,  800,  465,  486,  884,  405,  987,  652,  116,  432,  207,  699,    0,  647,  968,  803,  527,  165,  307,  173,  894,  529,  761,   88,  191,  295,  780,  154,  560,  250,  785,  320,  571,  981,  787,  118,  766,  445,  539,  387,  901,  982,  968,  859,  365,  829,  580,  322,  596,  921,  315,  433,  760,  507, 1075,  693,  500,  377,  597,  865,  471,  448,  693,  538,  274,  985,  722,  521,  933,  393,  207,  222,   70,  663,  773,  828,   80,  296,  418, 1022,  738,  206,  167,  896, 1029,  595, 1011,  563,  682,  359,  944,  667,  311],
        [  185,    0,  135,  495,  670,  310,  238,  444,  557,  450,  475,  467,  325,  468,  264,  504,  178,  698,  393,  410,  243,  310,  676,  381,  677,  379,  432,  619,  329,  468,   78,  647,    0,  429,  319,  358,  483,  344,  475,  444,  128,  417,  564,  522,  673,  134,  505,   96,  465,  148,  565,  512,  335,  348,  606,  313,  393,  314,  686,  329,  372,  416,  248,  729,  231,  230,  611,  202,  288,  346,  571,  407,  182,  586,  386,  338,  480,  430,  220,  493,  444,  230,  402,  697,  345,  204,  255,  332,  369,  607,  565,  599,  294,  139,  210,  577,  380,  237,  455,  213,  619,  611,  251,  587,  505,  506,  400,  257,  386,  305,  417,  361],
        [  507,    0,  445,  643,  868,  420,  439,  847,  610,  513,  715,  260,  643,  897,  277,  324,  271,  925,   98,  749,  189,  735,  762,  691,  810,  548,  403,  978,  751,  762,  351,  968,  429,    0,  666,  787,  816,  709,  812,  771,  541,  805,  900,  897, 1072,  381,  815,  462,  852,  311,  752,  940,  356,  197,  887,  206,  819,  441, 1099,  587,  158,  661,  205,  890,  206,  657, 1019,  374,  450,  658,  994,  794,  604,  165,  328,  766,  653,  855,  371,  598,  580,  275,  483, 1090,  279,  580,  683,  142,  585,  846,  805,  905,  703,  429,  471,  888,  765,  628,  665,  580,  858,  869,  375,  200,  514,   87,  460,  658,  797,  426,  377,  747],
        [  461,    0,  227,  781,  916,  625,  546,  513,  862,  760,  211,  772,   51,  396,  576,  815,  477,  925,  664,  593,  512,  342,  967,   82,  951,  245,  750,  732,  375,  679,  367,  803,  319,  666,    0,  305,  654,  516,  643,  126,  338,  156,  716,  627,  703,  289,  696,  388,  562,  363,  827,  392,  381,  647,  805,  613,  389,  626,  673,  138,  546,  172,  462,  988,  467,  225,  629,  519,  261,  573,  532,  146,  319,  830,  703,  318,  759,  299,  303,  792,  739,  540,  713,  738,  448,  117,  283,  532,  648,  836,  799,  778,  148,  241,  198,  754,  508,  415,  229,  106,  847,  827,  311,  853,  819,  752,  714,  122,  453,  297,  735,  494],
        [  365,    0,  384,  628,  699,  562,  478,  221,  741,  664,  511,  793,  354,  114,  590,  815,  529,  688,  747,  358,  600,   88,  805,  380,  766,  535,  703,  441,  109,  454,  436,  527,  358,  787,  305,    0,  400,  291,  389,  374,  263,  235,  443,  339,  399,  438,  451,  350,  278,  490,  637,  156,  613,  689,  555,  654,   86,  553,  374,  432,  716,  476,  598,  780,  586,  135,  325,  493,  510,  382,  238,  234,  198,  943,  686,   36,  598,   96,  502,  662,  609,  564,  625,  434,  656,  272,  106,  682,  503,  608,  580,  517,  159,  402,  417,  493,  252,  242,  533,  285,  618,  590,  525,  939,  733,  863,  636,  197,  170,  544,  698,  245],
        [  321,    0,  598,  328,  309,  424,  379,  203,  459,  436,  862,  692,  692,  409,  544,  682,  559,  290,  737,   74,  643,  326,  463,  735,  400,  827,  534,  167,  295,   90,  535,  165,  483,  816,  654,  400,    0,  144,   11,  753,  366,  630,   85,  130,  317,  616,   56,  396,  148,  622,  281,  480,  817,  644,  156,  620,  328,  404,  389,  744,  822,  814,  698,  394,  669,  430,  304,  443,  758,  159,  378,  627,  348,  933,  564,  369,  293,  482,  701,  386,  348,  542,  422,  315,  822,  566,  373,  773,  267,  215,  197,  125,  520,  609,  666,  101,  151,  256,  868,  582,  224,  192,  732,  893,  500,  866,  446,  533,  233,  781,  545,  162],
        [  202,    0,  455,  348,  412,  355,  289,  166,  471,  414,  723,  622,  552,  335,  448,  624,  442,  412,  638,   78,  527,  207,  518,  597,  475,  683,  487,  278,  183,  168,  403,  307,  344,  709,  516,  291,  144,    0,  135,  620,  223,  508,  221,  189,  370,  476,  181,  264,  148,  487,  346,  405,  678,  552,  290,  524,  239,  339,  415,  601,  697,  673,  571,  491,  544,  294,  328,  341,  615,  101,  353,  504,  205,  839,  497,  257,  315,  383,  561,  391,  341,  438,  385,  383,  687,  423,  241,  650,  237,  325,  293,  268,  389,  467,  522,  244,   69,  112,  726,  439,  336,  313,  591,  809,  483,  766,  404,  396,  152,  638,  490,   59],
        [  314,    0,  589,  332,  319,  422,  376,  194,  463,  438,  852,  691,  682,  400,  541,  681,  553,  300,  733,   66,  637,  315,  470,  725,  408,  818,  534,  169,  285,   95,  528,  173,  475,  812,  643,  389,   11,  135,    0,  742,  357,  620,   91,  126,  314,  607,   65,  389,  139,  614,  288,  470,  809,  640,  167,  616,  318,  402,  384,  734,  816,  804,  691,  403,  663,  419,  299,  439,  749,  154,  370,  616,  338,  930,  562,  358,  297,  472,  693,  389,  350,  537,  423,  314,  814,  556,  363,  767,  267,  225,  206,  136,  510,  600,  656,  111,  140,  247,  858,  572,  234,  202,  723,  891,  503,  862,  446,  523,  223,  772,  545,  151],
        [  583,    0,  345,  901, 1027,  750,  671,  593,  986,  885,  162,  893,  130,  441,  699,  937,  598, 1031,  778,  697,  629,  430, 1087,   82, 1069,  281,  875,  814,  463,  787,  490,  894,  444,  771,  126,  374,  753,  620,  742,    0,  459,  153,  808,  711,  760,  404,  798,  512,  647,  478,  943,  417,  457,  767,  907,  733,  459,  751,  715,  194,  640,  162,  569, 1102,  579,  328,  685,  644,  338,  685,  575,  149,  432,  934,  827,  396,  879,  336,  401,  915,  862,  663,  838,  797,  531,  242,  381,  633,  768,  944,  909,  876,  233,  357,  301,  851,  604,  526,  208,  231,  956,  933,  402,  964,  944,  857,  839,  228,  537,  371,  860,  592],
        [  127,    0,  233,  443,  587,  314,  230,  317,  531,  437,  529,  531,  363,  365,  328,  555,  274,  605,  490,  294,  352,  197,  629,  415,  614,  467,  454,  494,  211,  364,  199,  529,  128,  541,  338,  263,  366,  223,  357,  459,    0,  389,  444,  395,  546,  254,  394,   87,  337,  276,  492,  418,  456,  427,  500,  393,  280,  310,  562,  395,  498,  475,  372,  655,  351,  162,  486,  232,  393,  247,  454,  381,   66,  691,  428,  235,  421,  348,  339,  458,  404,  302,  391,  569,  471,  227,  157,  456,  310,  514,  474,  487,  255,  244,  302,  463,  254,  113,  523,  242,  526,  512,  368,  680,  501,  612,  398,  237,  261,  416,  445,  235],
        [  514,    0,  361,  819,  920,  700,  617,  455,  917,  825,  310,  883,  200,  290,  680,  920,  591,  916,  793,  581,  640,  305, 1003,  193,  974,  394,  836,  674,  335,  675,  481,  761,  417,  805,  156,  235,  630,  508,  620,  153,  389,    0,  677,  574,  610,  425,  679,  461,  512,  496,  846,  265,  537,  763,  786,  728,  319,  697,  563,  289,  694,  295,  601,  998,  602,  233,  535,  606,  416,  586,  423,   12,  345,  970,  799,  263,  793,  184,  452,  842,  788,  647,  780,  648,  601,  227,  271,  676,  687,  832,  801,  750,  134,  377,  348,  725,  480,  429,  349,  226,  843,  817,  463,  986,  889,  890,  785,  162,  404,  452,  824,  471],
        [  405,    0,  675,  383,  311,  503,  462,  228,  513,  503,  926,  769,  756,  432,  627,  756,  643,  272,  820,  157,  727,  378,  493,  796,  420,  900,  607,   95,  346,  153,  618,   88,  564,  900,  716,  443,   85,  221,   91,  808,  444,  677,    0,  118,  270,  696,   98,  479,  168,  704,  314,  499,  898,  725,  137,  703,  363,  483,  353,  813,  907,  880,  782,  396,  753,  492,  276,  527,  834,  242,  373,  675,  420, 1015,  641,  415,  349,  517,  781,  444,  412,  625,  494,  259,  904,  634,  433,  857,  341,  221,  219,   83,  577,  687,  741,   64,  208,  332,  934,  650,  225,  186,  811,  973,  564,  948,  518,  594,  274,  859,  620,  223],
        [  390,    0,  618,  457,  423,  530,  472,  119,  588,  559,  838,  799,  671,  316,  634,  794,  631,  389,  825,  165,  715,  286,  590,  707,  524,  829,  650,  106,  253,  220,  586,  191,  522,  897,  627,  339,  130,  189,  126,  711,  395,  574,  118,    0,  192,  648,  180,  449,   66,  668,  408,  383,  849,  737,  252,  711,  256,  511,  259,  736,  883,  796,  757,  509,  731,  408,  174,  528,  774,  257,  257,  573,  357, 1026,  671,  315,  422,  406,  731,  513,  473,  626,  541,  198,  866,  557,  348,  837,  384,  330,  320,  200,  483,  632,  678,  180,  142,  285,  852,  573,  336,  298,  760,  993,  625,  954,  563,  507,  175,  801,  658,  161],
        [  568,    0,  749,  644,  574,  720,  658,  230,  775,  751,  906,  988,  752,  320,  817,  986,  803,  523, 1006,  356,  886,  385,  762,  776,  688,  930,  842,  184,  356,  406,  744,  295,  673, 1072,  703,  399,  317,  370,  314,  760,  546,  610,  270,  192,    0,  789,  358,  614,  223,  821,  583,  362,  983,  921,  398,  893,  318,  701,   94,  829, 1043,  874,  917,  657,  895,  509,   75,  710,  893,  447,  195,  612,  495, 1207,  861,  390,  609,  426,  866,  702,  664,  805,  733,   40, 1011,  661,  453, 1000,  576,  487,  488,  341,  557,  764,  797,  330,  309,  446,  931,  675,  490,  450,  893, 1179,  816, 1134,  755,  593,  288,  924,  850,  326],
        [  316,    0,   64,  612,  798,  405,  348,  562,  659,  548,  390,  493,  275,  551,  313,  543,  206,  830,  376,  543,  226,  410,  789,  327,  797,  264,  505,  748,  435,  601,  114,  780,  134,  381,  289,  438,  616,  476,  607,  404,  254,  425,  696,  648,  789,    0,  639,  228,  588,   75,  690,  581,  203,  366,  739,  334,  491,  414,  792,  243,  281,  330,  177,  854,  179,  303,  723,  293,  163,  480,  667,  414,  295,  545,  445,  425,  601,  490,   86,  603,  557,  277,  500,  815,  223,  200,  346,  255,  493,  738,  696,  733,  328,   49,  112,  711,  507,  366,  358,  200,  751,  744,  117,  565,  594,  466,  493,  281,  501,  174,  485,  488],
        [  333,    0,  626,  287,  254,  410,  376,  258,  418,  405,  903,  674,  732,  464,  539,  659,  565,  238,  731,  104,  647,  375,  411,  777,  346,  860,  510,  193,  345,   56,  552,  154,  505,  815,  696,  451,   56,  181,   65,  798,  394,  679,   98,  180,  358,  639,    0,  414,  203,  639,  229,  535,  839,  635,  109,  614,  381,  389,  435,  781,  831,  853,  708,  339,  678,  473,  353,  443,  786,  164,  431,  676,  384,  924,  546,  420,  253,  536,  724,  347,  315,  540,  397,  353,  839,  603,  418,  781,  245,  161,  143,   96,  566,  636,  696,   75,  201,  289,  906,  619,  170,  139,  755,  880,  466,  859,  421,  576,  286,  807,  523,  209],
        [   90,    0,  229,  404,  574,  241,  159,  386,  475,  373,  561,  444,  403,  451,  241,  470,  192,  603,  407,  323,  274,  283,  588,  458,  584,  473,  376,  541,  293,  375,  140,  560,   96,  462,  388,  350,  396,  264,  389,  512,   87,  461,  479,  449,  614,  228,  414,    0,  397,  226,  470,  505,  425,  340,  513,  307,  364,  240,  638,  418,  435,  503,  308,  634,  283,  243,  558,  148,  384,  253,  535,  452,  153,  608,  344,  322,  387,  434,  313,  408,  356,  215,  326,  634,  426,  272,  244,  389,  275,  511,  469,  509,  329,  235,  305,  488,  310,  168,  545,  284,  524,  517,  344,  595,  434,  530,  328,  302,  335,  401,  365,  291],
        [  346,    0,  557,  458,  456,  501,  437,   60,  588,  547,  773,  769,  606,  266,  595,  769,  583,  430,  784,  151,  667,  221,  606,  642,  547,  764,  629,  171,  188,  230,  532,  250,  465,  852,  562,  278,  148,  148,  139,  647,  337,  512,  168,   66,  223,  588,  203,  397,    0,  612,  425,  336,  788,  699,  293,  671,  196,  484,  270,  671,  830,  731,  704,  541,  679,  343,  182,  488,  711,  234,  233,  511,  295,  985,  643,  252,  423,  349,  670,  510,  466,  584,  523,  238,  808,  493,  283,  785,  369,  362,  345,  247,  419,  571,  615,  224,   88,  230,  787,  508,  370,  335,  699,  957,  615,  912,  544,  442,  111,  738,  635,  106],
        [  307,    0,  137,  579,  777,  360,  314,  592,  613,  501,  457,  422,  349,  603,  251,  473,  143,  814,  302,  549,  152,  452,  749,  401,  765,  318,  447,  764,  474,  596,   88,  785,  148,  311,  363,  490,  622,  487,  614,  478,  276,  496,  704,  668,  821,   75,  639,  226,  612,    0,  665,  639,  208,  295,  734,  264,  535,  372,  831,  313,  228,  398,  110,  827,  106,  356,  758,  251,  210,  476,  713,  485,  328,  474,  382,  474,  572,  550,  117,  563,  520,  215,  454,  845,  201,  271,  392,  193,  468,  724,  681,  734,  393,  123,  182,  713,  527,  384,  421,  271,  737,  734,  144,  492,  542,  394,  444,  348,  534,  211,  425,  508],
        [  382,    0,  699,  112,  118,  336,  353,  475,  215,  254, 1021,  552,  854,  673,  485,  518,  551,  178,  657,  287,  620,  551,  183,  906,  129,  943,  375,  406,  529,  196,  582,  320,  565,  752,  827,  637,  281,  346,  288,  943,  492,  846,  314,  408,  583,  690,  229,  470,  425,  665,    0,  744,  873,  556,  204,  547,  581,  317,  663,  883,  811,  965,  703,  165,  669,  619,  582,  422,  851,  261,  657,  841,  512,  826,  435,  602,  100,  729,  772,  170,  173,  501,  272,  573,  851,  719,  576,  758,  198,  121,   99,  255,  719,  703,  774,  258,  396,  420, 1011,  734,  127,  159,  802,  765,  293,  774,  297,  716,  488,  864,  396,  397],
        [  514,    0,  524,  752,  788,  711,  628,  277,  873,  804,  573,  947,  442,   72,  745,  968,  684,  765,  902,  458,  755,  230,  921,  451,  871,  637,  852,  467,  235,  551,  589,  571,  512,  940,  392,  156,  480,  405,  470,  417,  418,  265,  499,  383,  362,  581,  535,  505,  336,  639,  744,    0,  743,  844,  628,  810,  168,  700,  303,  530,  862,  553,  748,  873,  737,  284,  291,  647,  632,  504,  168,  270,  353, 1097,  838,  184,  720,   96,  638,  793,  741,  719,  767,  401,  793,  398,  262,  831,  635,  695,  674,  580,  266,  541,  544,  558,  349,  384,  609,  407,  703,  670,  658, 1094,  873, 1017,  781,  313,  257,  667,  848,  350],
        [  511,    0,  235,  785,  985,  561,  521,  759,  811,  699,  368,  561,  343,  724,  434,  622,  335, 1021,  402,  744,  299,  600,  951,  376,  971,  198,  630,  949,  628,  799,  293,  981,  335,  356,  381,  613,  817,  678,  809,  457,  456,  537,  898,  849,  983,  203,  839,  425,  788,  208,  873,  743,    0,  442,  937,  420,  677,  575,  980,  264,  203,  320,  204, 1034,  235,  482,  915,  456,  122,  678,  849,  526,  494,  507,  557,  607,  779,  648,  119,  766,  726,  403,  653, 1011,   81,  346,  533,  219,  676,  931,  888,  933,  478,  220,  200,  911,  708,  568,  314,  337,  943,  939,   91,  556,  732,  438,  640,  430,  697,   87,  605,  689],
        [  357,    0,  422,  447,  673,  230,  266,  704,  418,  318,  751,  128,  639,  791,  105,  182,  172,  731,  101,  580,  149,  622,  569,  693,  615,  602,  212,  809,  630,  581,  282,  787,  348,  197,  647,  689,  644,  552,  640,  767,  427,  763,  725,  737,  921,  366,  635,  340,  699,  295,  556,  844,  442,    0,  699,   35,  703,  251,  960,  607,  293,  691,  240,  694,  212,  572,  875,  213,  494,  487,  870,  752,  492,  290,  135,  662,  458,  770,  400,  402,  384,  126,  286,  934,  383,  540,  583,  246,  397,  654,  613,  722,  641,  411,  476,  707,  614,  491,  712,  546,  665,  679,  418,  259,  324,  225,  264,  603,  662,  483,  186,  598],
        [  427,    0,  730,  296,  177,  470,  452,  352,  416,  433, 1012,  721,  841,  558,  610,  697,  649,  138,  798,  212,  729,  481,  370,  886,  292,  966,  548,  215,  451,  139,  647,  118,  606,  887,  805,  555,  156,  290,  167,  907,  500,  786,  137,  252,  398,  739,  109,  513,  293,  734,  204,  628,  937,  699,    0,  682,  482,  449,  486,  889,  917,  962,  797,  261,  765,  582,  412,  522,  890,  260,  508,  782,  492,  984,  596,  525,  268,  636,  825,  359,  342,  616,  436,  382,  932,  712,  527,  865,  303,   91,  106,   58,  674,  739,  801,   73,  306,  397, 1014,  728,   92,   52,  856,  932,  484,  924,  462,  685,  388,  910,  565,  316],
        [  327,    0,  389,  439,  664,  214,  241,  674,  420,  316,  721,  160,  606,  758,   77,  210,  138,  720,  118,  555,  123,  589,  571,  660,  612,  575,  219,  784,  598,  560,  248,  766,  313,  206,  613,  654,  620,  524,  616,  733,  393,  728,  703,  711,  893,  334,  614,  307,  671,  264,  547,  810,  420,   35,  682,    0,  670,  235,  930,  576,  284,  661,  217,  689,  187,  537,  846,  183,  466,  463,  838,  717,  459,  316,  143,  628,  448,  735,  372,  398,  376,   92,  281,  907,  365,  506,  548,  235,  380,  640,  599,  702,  606,  379,  445,  687,  585,  459,  683,  512,  652,  663,  391,  290,  330,  246,  259,  568,  631,  457,  193,  569],
        [  358,    0,  443,  585,  633,  551,  470,  138,  705,  638,  596,  798,  436,   99,  600,  813,  553,  617,  770,  296,  630,   84,  756,  465,  709,  613,  691,  356,   74,  391,  471,  445,  393,  819,  389,   86,  328,  239,  318,  459,  280,  319,  363,  256,  318,  491,  381,  364,  196,  535,  581,  168,  677,  703,  482,  670,    0,  539,  304,  512,  762,  560,  640,  716,  624,  195,  245,  497,  580,  337,  178,  318,  216,  970,  683,   73,  553,  155,  562,  625,  574,  578,  603,  352,  712,  344,  145,  725,  468,  541,  516,  440,  242,  460,  484,  416,  186,  223,  617,  358,  550,  519,  587,  958,  708,  891,  617,  276,   96,  612,  689,  185],
        [  190,    0,  442,  215,  434,   22,   81,  503,  245,  137,  788,  289,  638,  636,  169,  286,  242,  487,  350,  348,  305,  471,  378,  693,  399,  677,  153,  571,  467,  334,  300,  539,  314,  441,  626,  553,  404,  339,  402,  751,  310,  697,  483,  511,  701,  414,  389,  240,  484,  372,  317,  700,  575,  251,  449,  235,  539,    0,  753,  641,  495,  728,  391,  469,  357,  471,  665,  122,  575,  255,  685,  689,  364,  537,  161,  520,  218,  646,  486,  192,  153,  185,   88,  709,  543,  509,  456,  443,  147,  406,  364,  473,  564,  441,  515,  460,  406,  317,  765,  521,  418,  429,  515,  491,  194,  475,   89,  541,  475,  580,  153,  393],
        [  603,    0,  746,  716,  662,  770,  702,  256,  847,  814,  868, 1036,  722,  278,  855, 1038,  829,  613, 1039,  417,  911,  382,  844,  741,  773,  909,  898,  273,  358,  479,  760,  387,  686, 1099,  673,  374,  389,  415,  384,  715,  562,  563,  353,  259,   94,  792,  435,  638,  270,  831,  663,  303,  980,  960,  486,  930,  304,  753,    0,  804, 1057,  841,  933,  745,  913,  499,   88,  748,  882,  503,  142,  567,  505, 1241,  911,  374,  681,  381,  865,  772,  730,  840,  792,  127, 1014,  645,  448, 1017,  637,  573,  570,  429,  530,  763,  787,  416,  348,  473,  898,  658,  577,  537,  890, 1218,  881, 1165,  813,  570,  303,  915,  904,  363],
        [  503,    0,  200,  821,  981,  635,  566,  626,  885,  777,  149,  734,   90,  530,  555,  785,  448,  999,  604,  678,  462,  453, 1004,  113, 1000,  107,  745,  841,  486,  756,  349,  901,  329,  587,  138,  432,  744,  601,  734,  194,  395,  289,  813,  736,  829,  243,  781,  418,  671,  313,  883,  530,  264,  607,  889,  576,  512,  641,  804,    0,  450,   88,  391, 1047,  406,  328,  755,  523,  145,  641,  665,  279,  397,  748,  687,  440,  804,  436,  218,  822,  772,  519,  728,  863,  338,  180,  388,  447,  692,  908,  869,  869,  275,  204,  132,  845,  606,  492,  129,  164,  920,  905,  213,  783,  828,  673,  724,  237,  564,  178,  726,  591],
        [  502,    0,  342,  709,  928,  477,  468,  814,  703,  597,  568,  394,  516,  829,  330,  457,  268,  977,  224,  751,  191,  679,  853,  558,  888,  399,  503,  974,  700,  783,  300,  982,  372,  158,  546,  716,  822,  697,  816,  640,  498,  694,  907,  883, 1043,  281,  831,  435,  830,  228,  811,  862,  203,  293,  917,  284,  762,  495, 1057,  450,    0,  517,  127,  962,  154,  581,  983,  397,  307,  668,  940,  683,  553,  305,  425,  701,  712,  771,  243,  675,  646,  310,  557, 1066,  124,  477,  619,   53,  625,  891,  848,  925,  608,  324,  348,  906,  744,  601,  516,  473,  903,  908,  239,  355,  613,  237,  538,  560,  758,  279,  476,  725],
        [  586,    0,  288,  906, 1061,  722,  653,  683,  972,  864,   61,  819,  125,  564,  642,  871,  535, 1076,  684,  750,  545,  511, 1090,  103, 1084,  128,  833,  901,  544,  832,  437,  968,  416,  661,  172,  476,  814,  673,  804,  162,  475,  295,  880,  796,  874,  330,  853,  503,  731,  398,  965,  553,  320,  691,  962,  661,  560,  728,  841,   88,  517,    0,  470, 1128,  487,  389,  800,  611,  212,  719,  700,  287,  470,  819,  774,  489,  888,  463,  296,  908,  858,  606,  816,  910,  399,  251,  449,  520,  776,  985,  947,  939,  319,  292,  219,  915,  672,  566,   58,  235,  998,  981,  287,  859,  916,  746,  812,  289,  622,  238,  814,  657],
        [  378,    0,  241,  606,  819,  375,  353,  688,  617,  507,  527,  362,  441,  711,  237,  420,  152,  863,  215,  626,   97,  557,  762,  490,  790,  369,  429,  848,  577,  662,  174,  859,  248,  205,  462,  598,  698,  571,  691,  569,  372,  601,  782,  757,  917,  177,  708,  308,  704,  110,  703,  748,  204,  240,  797,  217,  640,  391,  933,  391,  127,  470,    0,  859,   35,  465,  857,  282,  262,  545,  817,  590,  429,  370,  355,  581,  605,  659,  174,  579,  544,  209,  463,  939,  155,  377,  499,   85,  511,  776,  733,  803,  502,  224,  269,  783,  617,  474,  482,  376,  788,  790,  186,  395,  534,  290,  447,  456,  632,  247,  404,  598],
        [  546,    0,  863,  254,   86,  486,  513,  597,  297,  378, 1183,  668, 1016,  802,  633,  624,  708,  139,  793,  422,  773,  698,  169, 1067,   87, 1107,  494,  474,  672,  327,  745,  365,  729,  890,  988,  780,  394,  491,  403, 1102,  655,  998,  396,  509,  657,  854,  339,  634,  541,  827,  165,  873, 1034,  694,  261,  689,  716,  469,  745, 1047,  962, 1128,  859,    0,  825,  775,  672,  580, 1015,  417,  765,  993,  670,  946,  565,  746,  255,  869,  935,  292,  317,  653,  409,  637, 1010,  881,  728,  910,  362,  180,  201,  317,  874,  868,  938,  333,  532,  576, 1175,  896,  173,  211,  965,  878,  393,  903,  431,  874,  621, 1027,  519,  536],
        [  349,    0,  242,  572,  785,  340,  319,  666,  583,  472,  545,  337,  450,  697,  203,  394,  119,  830,  200,  597,   65,  540,  728,  501,  755,  392,  396,  821,  559,  631,  154,  829,  231,  206,  467,  586,  669,  544,  663,  579,  351,  602,  753,  731,  895,  179,  678,  283,  679,  106,  669,  737,  235,  212,  765,  187,  624,  357,  913,  406,  154,  487,   35,  825,    0,  454,  836,  249,  284,  515,  801,  591,  411,  369,  323,  567,  571,  651,  192,  545,  510,  175,  429,  916,  189,  376,  484,  106,  478,  743,  700,  772,  497,  227,  280,  753,  592,  450,  503,  377,  755,  758,  208,  387,  501,  289,  413,  453,  612,  272,  371,  574],
        [  284,    0,  251,  587,  700,  476,  391,  299,  685,  595,  434,  683,  265,  248,  478,  712,  406,  704,  622,  370,  473,  127,  772,  306,  746,  425,  615,  514,  159,  459,  307,  580,  230,  657,  225,  135,  430,  294,  419,  328,  162,  233,  492,  408,  509,  303,  473,  243,  343,  356,  619,  284,  482,  572,  582,  537,  195,  471,  499,  328,  581,  389,  465,  775,  454,    0,  438,  390,  385,  360,  368,  226,  113,  815,  586,  126,  561,  200,  369,  609,  555,  449,  551,  541,  522,  153,   61,  549,  455,  616,  582,  554,  101,  268,  289,  530,  284,  200,  444,  168,  628,  606,  393,  816,  661,  735,  558,  104,  236,  417,  606,  270],
        [  519,    0,  681,  630,  587,  683,  616,  172,  761,  727,  831,  949,  678,  246,  771,  951,  749,  544,  956,  329,  831,  316,  763,  701,  695,  857,  811,  207,  288,  394,  684,  322,  611, 1019,  629,  325,  304,  328,  299,  685,  486,  535,  276,  174,   75,  723,  353,  558,  182,  758,  582,  291,  915,  875,  412,  846,  245,  665,   88,  755,  983,  800,  857,  672,  836,  438,    0,  663,  823,  415,  126,  538,  431, 1158,  824,  317,  595,  352,  799,  685,  643,  756,  705,  113,  946,  589,  383,  941,  549,  496,  491,  356,  483,  697,  727,  340,  262,  391,  857,  603,  501,  462,  825, 1133,  794, 1083,  725,  519,  225,  854,  816,  278],
        [  145,    0,  324,  329,  537,  113,   72,  492,  366,  256,  671,  302,  526,  589,  108,  324,  131,  582,  298,  376,  207,  420,  499,  582,  515,  556,  232,  605,  424,  392,  179,  596,  202,  374,  519,  493,  443,  341,  439,  644,  232,  606,  527,  528,  710,  293,  443,  148,  488,  251,  422,  647,  456,  213,  522,  183,  497,  122,  748,  523,  397,  611,  282,  580,  249,  390,  663,    0,  454,  285,  660,  596,  295,  498,  196,  463,  325,  580,  365,  312,  270,   99,  207,  724,  430,  403,  389,  345,  230,  495,  452,  535,  475,  322,  396,  518,  402,  280,  646,  413,  507,  512,  394,  471,  306,  426,  201,  445,  451,  459,  219,  386],
        [  473,    0,  160,  774,  958,  565,  510,  675,  819,  708,  266,  620,  221,  619,  460,  675,  353,  986,  476,  687,  346,  508,  951,  256,  959,  109,  657,  877,  539,  752,  276,  921,  288,  450,  261,  510,  758,  615,  749,  338,  393,  416,  834,  774,  893,  163,  786,  384,  711,  210,  851,  632,  122,  494,  890,  466,  580,  575,  882,  145,  307,  212,  262, 1015,  284,  385,  823,  454,    0,  632,  748,  406,  418,  608,  591,  509,  763,  536,   95,  765,  719,  425,  660,  924,  194,  239,  441,  309,  654,  894,  853,  879,  366,  151,   97,  856,  635,  503,  220,  227,  907,  898,   77,  648,  751,  535,  651,  320,  612,   37,  635,  617],
        [  170,    0,  473,  249,  344,  273,  222,  262,  371,  316,  772,  543,  603,  434,  387,  539,  403,  359,  579,   94,  486,  295,  424,  652,  389,  712,  396,  322,  276,  122,  389,  315,  346,  658,  573,  382,  159,  101,  154,  685,  247,  586,  242,  257,  447,  480,  164,  253,  234,  476,  261,  504,  678,  487,  260,  463,  337,  255,  503,  641,  668,  719,  545,  417,  515,  360,  415,  285,  632,    0,  451,  580,  254,  777,  415,  347,  217,  476,  566,  291,  241,  384,  290,  455,  676,  469,  315,  618,  138,  268,  229,  259,  459,  481,  545,  239,  167,  160,  768,  485,  280,  267,  596,  739,  385,  708,  311,  458,  252,  651,  403,  159],
        [  516,    0,  618,  688,  680,  699,  624,  190,  816,  766,  727,  957,  582,  137,  766,  967,  726,  645,  941,  380,  805,  261,  838,  600,  777,  770,  836,  320,  244,  462,  648,  433,  571,  994,  532,  238,  378,  353,  370,  575,  454,  423,  373,  257,  195,  667,  431,  535,  233,  713,  657,  168,  849,  870,  508,  838,  178,  685,  142,  665,  940,  700,  817,  765,  801,  368,  126,  660,  748,  451,    0,  427,  391, 1143,  837,  243,  653,  240,  736,  737,  690,  746,  737,  234,  888,  510,  322,  902,  588,  586,  574,  455,  390,  635,  654,  436,  285,  380,  757,  522,  593,  555,  760, 1127,  835, 1065,  755,  432,  211,  781,  837,  295],
        [  506,    0,  350,  812,  915,  691,  608,  454,  910,  817,  304,  873,  190,  293,  670,  910,  580,  912,  782,  577,  629,  302,  997,  185,  968,  384,  827,  674,  332,  670,  471,  760,  407,  794,  146,  234,  627,  504,  616,  149,  381,   12,  675,  573,  612,  414,  676,  452,  511,  485,  841,  270,  526,  752,  782,  717,  318,  689,  567,  279,  683,  287,  590,  993,  591,  226,  538,  596,  406,  580,  427,    0,  338,  958,  789,  260,  786,  188,  441,  834,  780,  636,  772,  650,  590,  216,  265,  665,  680,  828,  796,  747,  126,  366,  337,  723,  477,  422,  341,  215,  839,  813,  452,  975,  881,  879,  777,  152,  402,  442,  815,  467],
        [  175,    0,  262,  476,  598,  371,  286,  267,  574,  485,  521,  595,  351,  300,  392,  618,  338,  608,  555,  281,  415,  133,  661,  399,  637,  480,  511,  460,  149,  362,  257,  507,  182,  604,  319,  198,  348,  205,  338,  432,   66,  345,  420,  357,  495,  295,  384,  153,  295,  328,  512,  353,  494,  492,  492,  459,  216,  364,  505,  397,  553,  470,  429,  670,  411,  113,  431,  295,  418,  254,  391,  338,    0,  755,  489,  170,  450,  286,  376,  497,  443,  367,  442,  520,  517,  220,   94,  513,  343,  518,  481,  472,  212,  276,  323,  448,  218,   97,  522,  236,  530,  512,  405,  745,  551,  676,  450,  205,  207,  445,  504,  200],
        [  641,    0,  609,  714,  939,  515,  556,  987,  653,  574,  871,  279,  807, 1052,  392,  329,  417, 1003,  203,  870,  343,  887,  801,  853,  862,  703,  454, 1099,  900,  869,  509, 1075,  586,  165,  830,  943,  933,  839,  930,  934,  691,  970, 1015, 1026, 1207,  545,  924,  608,  985,  474,  826, 1097,  507,  290,  984,  316,  970,  537, 1241,  748,  305,  819,  370,  946,  369,  815, 1158,  498,  608,  777, 1143,  958,  755,    0,  392,  921,  731, 1014,  534,  661,  655,  403,  555, 1222,  427,  744,  838,  302,  683,  932,  893, 1009,  865,  593,  635,  996,  899,  769,  820,  744,  942,  959,  536,   86,  555,   81,  530,  821,  940,  582,  431,  882],
        [  326,    0,  490,  324,  550,  142,  214,  659,  283,  188,  835,  129,  704,  778,  132,  131,  240,  612,  230,  508,  259,  609,  435,  760,  483,  699,   78,  730,  610,  490,  340,  693,  386,  328,  703,  686,  564,  497,  562,  827,  428,  799,  641,  671,  861,  445,  546,  344,  643,  382,  435,  838,  557,  135,  596,  143,  683,  161,  911,  687,  425,  774,  355,  565,  323,  586,  824,  196,  591,  415,  837,  789,  489,  392,    0,  655,  340,  775,  497,  274,  264,  169,  164,  869,  506,  589,  583,  376,  301,  541,  502,  625,  670,  484,  555,  614,  564,  461,  802,  598,  551,  569,  519,  337,  189,  341,  139,  638,  627,  587,   51,  550],
        [  333,    0,  375,  593,  665,  530,  446,  198,  706,  630,  527,  764,  365,  132,  562,  785,  505,  657,  723,  325,  579,   53,  770,  396,  731,  541,  671,  419,   75,  420,  415,  500,  338,  766,  318,   36,  369,  257,  358,  396,  235,  263,  415,  315,  390,  425,  420,  322,  252,  474,  602,  184,  607,  662,  525,  628,   73,  520,  374,  440,  701,  489,  581,  746,  567,  126,  317,  463,  509,  347,  243,  260,  170,  921,  655,    0,  563,  131,  494,  627,  574,  537,  591,  424,  646,  272,   83,  666,  468,  575,  547,  488,  172,  392,  414,  463,  220,  208,  546,  286,  586,  558,  518,  914,  699,  841,  603,  204,  142,  541,  666,  212],
        [  302,    0,  615,   36,  217,  237,  259,  465,  167,  166,  945,  461,  782,  649,  385,  432,  454,  274,  559,  274,  522,  511,  211,  835,  197,  858,  285,  444,  493,  203,  491,  377,  480,  653,  759,  598,  293,  315,  297,  879,  421,  793,  349,  422,  609,  601,  253,  387,  423,  572,  100,  720,  779,  458,  268,  448,  553,  218,  681,  804,  712,  888,  605,  255,  571,  561,  595,  325,  763,  217,  653,  786,  450,  731,  340,  563,    0,  692,  681,   95,   77,  402,  177,  605,  755,  647,  524,  660,  113,  202,  166,  308,  662,  618,  690,  304,  376,  365,  932,  661,  212,  233,  711,  674,  218,  678,  202,  653,  465,  774,  304,  372],
        [  457,    0,  431,  723,  786,  654,  569,  290,  836,  759,  488,  878,  350,  106,  673,  903,  605,  772,  822,  447,  672,  183,  899,  362,  857,  543,  795,  501,  201,  542,  506,  597,  430,  855,  299,   96,  482,  383,  472,  336,  348,  184,  517,  406,  426,  490,  536,  434,  349,  550,  729,   96,  648,  770,  636,  735,  155,  646,  381,  436,  771,  463,  659,  869,  651,  200,  352,  580,  536,  476,  240,  188,  286, 1014,  775,  131,  692,    0,  544,  757,  704,  645,  719,  464,  699,  303,  192,  742,  598,  694,  668,  594,  171,  449,  449,  571,  338,  337,  520,  312,  704,  673,  563, 1015,  827,  934,  730,  219,  250,  572,  789,  334],
        [  401,    0,  119,  690,  881,  475,  425,  641,  729,  617,  354,  527,  275,  614,  366,  581,  259,  914,  388,  629,  252,  484,  863,  320,  876,  204,  563,  831,  511,  687,  190,  865,  220,  371,  303,  502,  701,  561,  693,  401,  339,  452,  781,  731,  866,   86,  724,  313,  670,  117,  772,  638,  119,  400,  825,  372,  562,  486,  865,  218,  243,  296,  174,  935,  192,  369,  799,  365,   95,  566,  736,  441,  376,  534,  497,  494,  681,  544,    0,  677,  633,  331,  570,  894,  156,  242,  418,  233,  574,  823,  780,  819,  376,  103,  106,  796,  590,  451,  312,  236,  835,  829,   31,  566,  658,  457,  560,  327,  580,   95,  541,  571],
        [  333,    0,  626,   63,  279,  206,  257,  548,   81,   87,  967,  385,  810,  723,  347,  349,  432,  346,  502,  360,  489,  575,  187,  864,  214,  865,  207,  539,  561,  297,  490,  471,  493,  598,  792,  662,  386,  391,  389,  915,  458,  842,  444,  513,  702,  603,  347,  408,  510,  563,  170,  793,  766,  402,  359,  398,  625,  192,  772,  822,  675,  908,  579,  292,  545,  609,  685,  312,  765,  291,  737,  834,  497,  661,  274,  627,   95,  757,  677,    0,   55,  371,  119,  699,  733,  677,  579,  624,  160,  287,  255,  402,  709,  626,  701,  399,  455,  422,  948,  690,  295,  321,  706,  597,  125,  614,  140,  694,  542,  771,  230,  449],
        [  279,    0,  577,   64,  289,  170,  210,  501,  133,   93,  916,  384,  758,  672,  317,  356,  394,  349,  485,  315,  457,  522,  233,  812,  246,  818,  208,  507,  508,  261,  444,  448,  444,  580,  739,  609,  348,  341,  350,  862,  404,  788,  412,  473,  664,  557,  315,  356,  466,  520,  173,  741,  726,  384,  342,  376,  574,  153,  730,  772,  646,  858,  544,  317,  510,  555,  643,  270,  719,  241,  690,  780,  443,  655,  264,  574,   77,  704,  633,   55,    0,  337,  100,  663,  696,  625,  526,  594,  107,  279,  242,  379,  655,  578,  652,  372,  407,  369,  899,  638,  289,  310,  662,  597,  153,  602,  125,  640,  492,  727,  227,  400],
        [  238,    0,  323,  400,  618,  167,  166,  585,  409,  298,  666,  237,  538,  666,   37,  275,   73,  668,  201,  474,  120,  497,  553,  594,  582,  533,  232,  704,  506,  489,  174,  693,  230,  275,  540,  564,  542,  438,  537,  663,  302,  647,  625,  626,  805,  277,  540,  215,  584,  215,  501,  719,  403,  126,  616,   92,  578,  185,  840,  519,  310,  606,  209,  653,  175,  449,  756,   99,  425,  384,  746,  636,  367,  403,  169,  537,  402,  645,  331,  371,  337,    0,  254,  820,  363,  429,  458,  258,  318,  584,  541,  631,  522,  316,  387,  615,  497,  369,  634,  436,  596,  603,  356,  382,  331,  329,  239,  486,  540,  423,  210,  480],
        [  267,    0,  529,  161,  387,   95,  167,  550,  160,   49,  875,  286,  725,  701,  229,  263,  318,  449,  387,  377,  371,  540,  300,  781,  332,  763,  114,  586,  532,  341,  386,  538,  402,  483,  713,  625,  422,  385,  423,  838,  391,  780,  494,  541,  733,  500,  397,  326,  523,  454,  272,  767,  653,  286,  436,  281,  603,   88,  792,  728,  557,  816,  463,  409,  429,  551,  705,  207,  660,  290,  737,  772,  442,  555,  164,  591,  177,  719,  570,  119,  100,  254,    0,  736,  617,  596,  531,  505,  157,  378,  340,  469,  646,  528,  602,  460,  454,  384,  852,  608,  388,  407,  597,  498,  110,  503,   26,  625,  530,  664,  129,  443],
        [  583,    0,  777,  639,  556,  728,  670,  254,  770,  751,  942,  997,  787,  358,  831,  992,  821,  502, 1021,  362,  905,  416,  749,  812,  673,  963,  847,  168,  386,  403,  766,  274,  697, 1090,  738,  434,  315,  383,  314,  797,  569,  648,  259,  198,   40,  815,  353,  634,  238,  845,  573,  401, 1011,  934,  382,  907,  352,  709,  127,  863, 1066,  910,  939,  637,  916,  541,  113,  724,  924,  455,  234,  650,  520, 1222,  869,  424,  605,  464,  894,  699,  663,  820,  736,    0, 1037,  693,  484, 1022,  579,  472,  476,  325,  592,  792,  827,  317,  326,  466,  967,  707,  474,  433,  921, 1190,  815, 1149,  758,  627,  315,  954,  855,  344],
        [  507,    0,  272,  758,  966,  528,  499,  784,  771,  661,  448,  497,  412,  768,  391,  559,  302, 1008,  332,  749,  250,  633,  916,  450,  942,  278,  581,  963,  658,  795,  288,  985,  345,  279,  448,  656,  822,  687,  814,  531,  471,  601,  904,  866, 1011,  223,  839,  426,  808,  201,  851,  793,   81,  383,  932,  365,  712,  543, 1014,  338,  124,  399,  155, 1010,  189,  522,  946,  430,  194,  676,  888,  590,  517,  427,  506,  646,  755,  699,  156,  733,  696,  363,  617, 1037,    0,  397,  568,  146,  657,  919,  875,  934,  530,  254,  255,  913,  724,  581,  394,  390,  931,  930,  139,  477,  688,  360,  601,  482,  723,  162,  556,  705],
        [  347,    0,  137,  668,  812,  508,  430,  450,  746,  644,  304,  664,  136,  381,  464,  704,  369,  826,  567,  500,  414,  278,  853,  189,  841,  273,  635,  663,  311,  581,  259,  722,  204,  580,  117,  272,  566,  423,  556,  242,  227,  227,  634,  557,  661,  200,  603,  272,  493,  271,  719,  398,  346,  540,  712,  506,  344,  509,  645,  180,  477,  251,  377,  881,  376,  153,  589,  403,  239,  469,  510,  216,  220,  744,  589,  272,  647,  303,  242,  677,  625,  429,  596,  693,  397,    0,  212,  454,  535,  735,  697,  690,  134,  154,  147,  666,  427,  316,  303,   17,  747,  730,  261,  760,  703,  664,  597,   86,  387,  273,  620,  411],
        [  267,    0,  299,  552,  651,  463,  378,  239,  657,  573,  493,  688,  324,  214,  484,  711,  423,  652,  641,  317,  496,   68,  735,  364,  704,  484,  604,  454,  100,  408,  333,  521,  255,  683,  283,  106,  373,  241,  363,  381,  157,  271,  433,  348,  453,  346,  418,  244,  283,  392,  576,  262,  533,  583,  527,  548,  145,  456,  448,  388,  619,  449,  499,  728,  484,   61,  383,  389,  441,  315,  322,  265,   94,  838,  583,   83,  524,  192,  418,  579,  526,  458,  531,  484,  568,  212,    0,  583,  422,  565,  532,  497,  149,  316,  344,  472,  226,  160,  504,  227,  577,  553,  443,  833,  641,  759,  541,  162,  176,  472,  598,  213],
        [  454,    0,  318,  657,  875,  424,  416,  771,  652,  545,  574,  353,  507,  795,  277,  416,  217,  924,  187,  702,  139,  641,  802,  552,  836,  408,  454,  926,  661,  732,  257,  933,  332,  142,  532,  682,  773,  650,  767,  633,  456,  676,  857,  837, 1000,  255,  781,  389,  785,  193,  758,  831,  219,  246,  865,  235,  725,  443, 1017,  447,   53,  520,   85,  910,  106,  549,  941,  345,  309,  618,  902,  665,  513,  302,  376,  666,  660,  742,  233,  624,  594,  258,  505, 1022,  146,  454,  583,    0,  573,  839,  796,  874,  582,  301,  335,  856,  698,  556,  524,  452,  851,  856,  235,  340,  564,  227,  487,  536,  716,  285,  427,  680],
        [  190,    0,  503,  134,  310,  168,  159,  400,  239,  179,  833,  429,  670,  566,  309,  416,  360,  353,  496,  221,  435,  416,  320,  723,  309,  747,  268,  432,  402,  190,  385,  393,  369,  585,  648,  503,  267,  237,  267,  768,  310,  687,  341,  384,  576,  493,  245,  275,  369,  468,  198,  635,  676,  397,  303,  380,  468,  147,  637,  692,  625,  776,  511,  362,  478,  455,  549,  230,  654,  138,  588,  680,  343,  683,  301,  468,  113,  598,  574,  160,  107,  318,  157,  579,  657,  535,  422,  573,    0,  267,  224,  327,  555,  507,  579,  314,  304,  264,  820,  549,  279,  286,  604,  636,  248,  621,  180,  544,  387,  666,  279,  296],
        [  423,    0,  737,  225,   94,  427,  424,  418,  336,  367, 1038,  662,  868,  624,  573,  632,  625,   92,  755,  251,  701,  528,  280,  916,  202,  978,  486,  305,  501,  158,  638,  207,  607,  846,  836,  608,  215,  325,  225,  944,  514,  832,  221,  330,  487,  738,  161,  511,  362,  724,  121,  695,  931,  654,   91,  640,  541,  406,  573,  908,  891,  985,  776,  180,  743,  616,  496,  495,  894,  268,  586,  828,  518,  932,  541,  575,  202,  694,  823,  287,  279,  584,  378,  472,  919,  735,  565,  839,  267,    0,   44,  147,  713,  744,  810,  158,  357,  422, 1035,  751,   13,   40,  854,  875,  411,  876,  403,  718,  445,  911,  505,  364],
        [  380,    0,  696,  192,  120,  385,  381,  399,  311,  332, 1000,  625,  831,  603,  530,  597,  582,  134,  713,  222,  658,  498,  274,  879,  205,  937,  450,  309,  472,  127,  595,  222,  565,  805,  799,  580,  197,  293,  206,  909,  474,  801,  219,  320,  488,  696,  143,  469,  345,  681,   99,  674,  888,  613,  106,  599,  516,  364,  570,  869,  848,  947,  733,  201,  700,  582,  491,  452,  853,  229,  574,  796,  481,  893,  502,  547,  166,  668,  780,  255,  242,  541,  340,  476,  875,  697,  532,  796,  224,   44,    0,  156,  680,  703,  769,  160,  331,  385,  996,  713,   56,   68,  811,  837,  380,  836,  365,  683,  421,  869,  468,  336],
        [  428,    0,  719,  339,  234,  494,  466,  306,  464,  471,  987,  752,  817,  512,  629,  732,  658,  190,  819,  193,  740,  447,  426,  859,  348,  951,  583,  158,  416,  143,  647,   70,  599,  905,  778,  517,  125,  268,  136,  876,  487,  750,   83,  200,  341,  733,   96,  509,  247,  734,  255,  580,  933,  722,   58,  702,  440,  473,  429,  869,  925,  939,  803,  317,  772,  554,  356,  535,  879,  259,  455,  747,  472, 1009,  625,  488,  308,  594,  819,  402,  379,  631,  469,  325,  934,  690,  497,  874,  327,  147,  156,    0,  643,  729,  788,   25,  273,  379,  992,  706,  149,  109,  849,  961,  526,  946,  495,  657,  348,  901,  598,  285],
        [  380,    0,  266,  687,  798,  567,  483,  367,  784,  691,  356,  759,  196,  256,  554,  792,  471,  800,  680,  465,  527,  199,  872,  225,  846,  380,  704,  588,  232,  556,  364,  663,  294,  703,  148,  159,  520,  389,  510,  233,  255,  134,  577,  483,  557,  328,  566,  329,  419,  393,  719,  266,  478,  641,  674,  606,  242,  564,  530,  275,  608,  319,  502,  874,  497,  101,  483,  475,  366,  459,  390,  126,  212,  865,  670,  172,  662,  171,  376,  709,  655,  522,  646,  592,  530,  134,  149,  582,  555,  713,  680,  643,    0,  284,  279,  619,  371,  300,  376,  142,  725,  701,  394,  874,  756,  785,  652,   49,  308,  402,  693,  359],
        [  324,    0,   18,  631,  809,  434,  370,  540,  686,  576,  353,  538,  228,  514,  352,  586,  247,  836,  424,  537,  273,  382,  811,  282,  814,  240,  541,  734,  409,  602,  146,  773,  139,  429,  241,  402,  609,  467,  600,  357,  244,  377,  687,  632,  764,   49,  636,  235,  571,  123,  703,  541,  220,  411,  739,  379,  460,  441,  763,  204,  324,  292,  224,  868,  227,  268,  697,  322,  151,  481,  635,  366,  276,  593,  484,  392,  618,  449,  103,  626,  578,  316,  528,  792,  254,  154,  316,  301,  507,  744,  703,  729,  284,    0,   75,  706,  492,  355,  325,  152,  757,  747,  130,  613,  626,  514,  522,  237,  478,  172,  522,  474],
        [  393,    0,   76,  704,  877,  508,  444,  578,  760,  651,  280,  603,  173,  526,  423,  653,  316,  902,  479,  595,  332,  412,  885,  222,  887,  169,  614,  781,  442,  665,  219,  828,  210,  471,  198,  417,  666,  522,  656,  301,  302,  348,  741,  678,  797,  112,  696,  305,  615,  182,  774,  544,  200,  476,  801,  445,  484,  515,  787,  132,  348,  219,  269,  938,  280,  289,  727,  396,   97,  545,  654,  337,  323,  635,  555,  414,  690,  449,  106,  701,  652,  387,  602,  827,  255,  147,  344,  335,  579,  810,  769,  788,  279,   75,    0,  764,  540,  410,  251,  138,  823,  812,  117,  663,  700,  558,  597,  231,  516,  128,  595,  523],
        [  407,    0,  696,  336,  248,  481,  450,  283,  463,  464,  962,  742,  792,  489,  613,  723,  640,  210,  804,  170,  722,  423,  433,  835,  358,  927,  574,  149,  391,  127,  626,   80,  577,  888,  754,  493,  101,  244,  111,  851,  463,  725,   64,  180,  330,  711,   75,  488,  224,  713,  258,  558,  911,  707,   73,  687,  416,  460,  416,  845,  906,  915,  783,  333,  753,  530,  340,  518,  856,  239,  436,  723,  448,  996,  614,  463,  304,  571,  796,  399,  372,  615,  460,  317,  913,  666,  472,  856,  314,  158,  160,   25,  619,  706,  764,    0,  248,  355,  968,  682,  162,  122,  827,  949,  521,  932,  485,  633,  324,  878,  588,  260],
        [  259,    0,  479,  410,  449,  423,  354,   97,  535,  482,  718,  688,  548,  277,  510,  692,  496,  438,  698,  111,  580,  176,  573,  589,  524,  695,  555,  243,  145,  205,  445,  296,  380,  765,  508,  252,  151,   69,  140,  604,  254,  480,  208,  142,  309,  507,  201,  310,   88,  527,  396,  349,  708,  614,  306,  585,  186,  406,  348,  606,  744,  672,  617,  532,  592,  284,  262,  402,  635,  167,  285,  477,  218,  899,  564,  220,  376,  338,  590,  455,  407,  497,  454,  326,  724,  427,  226,  698,  304,  357,  331,  273,  371,  492,  540,  248,    0,  144,  727,  443,  368,  339,  619,  872,  551,  825,  472,  387,   92,  662,  559,   19],
        [  137,    0,  344,  393,  502,  328,  248,  219,  501,  423,  618,  578,  447,  320,  386,  591,  358,  511,  567,  187,  441,  157,  576,  495,  547,  572,  469,  382,  151,  266,  302,  418,  237,  628,  415,  242,  256,  112,  247,  526,  113,  429,  332,  285,  446,  366,  289,  168,  230,  384,  420,  384,  568,  491,  397,  459,  223,  317,  473,  492,  601,  566,  474,  576,  450,  200,  391,  280,  503,  160,  380,  422,   97,  769,  461,  208,  365,  337,  451,  422,  369,  369,  384,  466,  581,  316,  160,  556,  264,  422,  385,  379,  300,  355,  410,  355,  144,    0,  618,  332,  434,  415,  481,  749,  492,  693,  397,  299,  172,  527,  467,  125],
        [  631,    0,  324,  948, 1109,  758,  692,  739, 1010,  901,   60,  838,  182,  621,  670,  892,  562, 1126,  696,  802,  564,  567, 1131,  159, 1128,  118,  863,  957,  600,  882,  469, 1022,  455,  665,  229,  533,  868,  726,  858,  208,  523,  349,  934,  852,  931,  358,  906,  545,  787,  421, 1011,  609,  314,  712, 1014,  683,  617,  765,  898,  129,  516,   58,  482, 1175,  503,  444,  857,  646,  220,  768,  757,  341,  522,  820,  802,  546,  932,  520,  312,  948,  899,  634,  852,  967,  394,  303,  504,  524,  820, 1035,  996,  992,  376,  325,  251,  968,  727,  618,    0,  287, 1048, 1032,  297,  864,  950,  749,  847,  346,  678,  240,  843,  712],
        [  361,    0,  136,  682,  827,  519,  442,  466,  759,  656,  288,  670,  121,  392,  472,  711,  375,  842,  570,  516,  417,  294,  867,  175,  856,  258,  645,  678,  326,  597,  265,  738,  213,  580,  106,  285,  582,  439,  572,  231,  242,  226,  650,  573,  675,  200,  619,  284,  508,  271,  734,  407,  337,  546,  728,  512,  358,  521,  658,  164,  473,  235,  376,  896,  377,  168,  603,  413,  227,  485,  522,  215,  236,  744,  598,  286,  661,  312,  236,  690,  638,  436,  608,  707,  390,   17,  227,  452,  549,  751,  713,  706,  142,  152,  138,  682,  443,  332,  287,    0,  763,  746,  253,  762,  714,  665,  608,   94,  403,  262,  629,  427],
        [  435,    0,  749,  234,   87,  438,  436,  427,  342,  376, 1050,  672,  880,  633,  584,  641,  637,   80,  766,  262,  713,  539,  280,  928,  200,  991,  495,  307,  511,  170,  651,  206,  619,  858,  847,  618,  224,  336,  234,  956,  526,  843,  225,  336,  490,  751,  170,  524,  370,  737,  127,  703,  943,  665,   92,  652,  550,  418,  577,  920,  903,  998,  788,  173,  755,  628,  501,  507,  907,  280,  593,  839,  530,  942,  551,  586,  212,  704,  835,  295,  289,  596,  388,  474,  931,  747,  577,  851,  279,   13,   56,  149,  725,  757,  823,  162,  368,  434, 1048,  763,    0,   41,  866,  885,  419,  887,  413,  730,  455,  924,  515,  374],
        [  429,    0,  739,  259,  126,  450,  441,  393,  373,  399, 1032,  692,  862,  599,  594,  665,  641,  100,  779,  237,  718,  512,  320,  908,  240,  979,  517,  267,  483,  150,  647,  167,  611,  869,  827,  590,  192,  313,  202,  933,  512,  817,  186,  298,  450,  744,  139,  517,  335,  734,  159,  670,  939,  679,   52,  663,  519,  429,  537,  905,  908,  981,  790,  211,  758,  606,  462,  512,  898,  267,  555,  813,  512,  959,  569,  558,  233,  673,  829,  321,  310,  603,  407,  433,  930,  730,  553,  856,  286,   40,   68,  109,  701,  747,  812,  122,  339,  415, 1032,  746,   41,    0,  860,  905,  446,  902,  433,  709,  424,  916,  536,  347],
        [  432,    0,  145,  719,  912,  503,  454,  669,  756,  644,  343,  544,  279,  636,  390,  600,  284,  945,  399,  659,  270,  510,  892,  320,  905,  185,  587,  861,  538,  718,  220,  896,  251,  375,  311,  525,  732,  591,  723,  402,  368,  463,  811,  760,  893,  117,  755,  344,  699,  144,  802,  658,   91,  418,  856,  391,  587,  515,  890,  213,  239,  287,  186,  965,  208,  393,  825,  394,   77,  596,  760,  452,  405,  536,  519,  518,  711,  563,   31,  706,  662,  356,  597,  921,  139,  261,  443,  235,  604,  854,  811,  849,  394,  130,  117,  827,  619,  481,  297,  253,  866,  860,    0,  573,  684,  461,  587,  346,  607,   68,  565,  601],
        [  616,    0,  628,  654,  876,  470,  521,  963,  583,  512,  913,  214,  835, 1044,  364,  255,  411,  942,  195,  833,  348,  877,  728,  884,  793,  748,  391, 1060,  887,  824,  512, 1029,  587,  200,  853,  939,  893,  809,  891,  964,  680,  986,  973,  993, 1179,  565,  880,  595,  957,  492,  765, 1094,  556,  259,  932,  290,  958,  491, 1218,  783,  355,  859,  395,  878,  387,  816, 1133,  471,  648,  739, 1127,  975,  745,   86,  337,  914,  674, 1015,  566,  597,  597,  382,  498, 1190,  477,  760,  833,  340,  636,  875,  837,  961,  874,  613,  663,  949,  872,  749,  864,  762,  885,  905,  573,    0,  486,  119,  473,  832,  920,  625,  370,  856],
        [  377,    0,  628,  188,  395,  195,  275,  647,   98,   70,  976,  277,  830,  806,  299,  232,  401,  465,  417,  466,  439,  648,  249,  886,  308,  856,  112,  658,  639,  414,  482,  595,  505,  514,  819,  733,  500,  483,  503,  944,  501,  889,  564,  625,  816,  594,  466,  434,  615,  542,  293,  873,  732,  324,  484,  330,  708,  194,  881,  828,  613,  916,  534,  393,  501,  661,  794,  306,  751,  385,  835,  881,  551,  555,  189,  699,  218,  827,  658,  125,  153,  331,  110,  815,  688,  703,  641,  564,  248,  411,  380,  526,  756,  626,  700,  521,  551,  492,  950,  714,  419,  446,  684,  486,    0,  516,  106,  734,  632,  752,  139,  542],
        [  567,    0,  529,  663,  889,  454,  487,  911,  614,  527,  800,  244,  729,  972,  322,  302,  339,  951,  129,  800,  263,  808,  765,  777,  821,  632,  410, 1030,  822,  805,  429, 1011,  506,   87,  752,  863,  866,  766,  862,  857,  612,  890,  948,  954, 1134,  466,  859,  530,  912,  394,  774, 1017,  438,  225,  924,  246,  891,  475, 1165,  673,  237,  746,  290,  903,  289,  735, 1083,  426,  535,  708, 1065,  879,  676,   81,  341,  841,  678,  934,  457,  614,  602,  329,  503, 1149,  360,  664,  759,  227,  621,  876,  836,  946,  785,  514,  558,  932,  825,  693,  749,  665,  887,  902,  461,  119,  516,    0,  478,  741,  864,  511,  385,  808],
        [  275,    0,  524,  185,  412,   90,  170,  569,  171,   60,  872,  260,  724,  715,  212,  238,  306,  474,  364,  399,  354,  553,  316,  780,  353,  755,   90,  610,  546,  366,  379,  563,  400,  460,  714,  636,  446,  404,  446,  839,  398,  785,  518,  563,  755,  493,  421,  328,  544,  444,  297,  781,  640,  264,  462,  259,  617,   89,  813,  724,  538,  812,  447,  431,  413,  558,  725,  201,  651,  311,  755,  777,  450,  530,  139,  603,  202,  730,  560,  140,  125,  239,   26,  758,  601,  597,  541,  487,  180,  403,  365,  495,  652,  522,  597,  485,  472,  397,  847,  608,  413,  433,  587,  473,  106,  478,    0,  629,  547,  654,  104,  461],
        [  363,    0,  219,  677,  800,  543,  460,  394,  768,  671,  332,  723,  164,  300,  519,  759,  432,  807,  638,  473,  485,  222,  863,  203,  842,  339,  676,  612,  255,  561,  323,  682,  257,  658,  122,  197,  533,  396,  523,  228,  237,  162,  594,  507,  593,  281,  576,  302,  442,  348,  716,  313,  430,  603,  685,  568,  276,  541,  570,  237,  560,  289,  456,  874,  453,  104,  519,  445,  320,  458,  432,  152,  205,  821,  638,  204,  653,  219,  327,  694,  640,  486,  625,  627,  482,   86,  162,  536,  544,  718,  683,  657,   49,  237,  231,  633,  387,  299,  346,   94,  730,  709,  346,  832,  734,  741,  629,    0,  333,  355,  664,  373],
        [  307,    0,  463,  498,  538,  489,  413,   64,  622,  562,  663,  747,  497,  186,  558,  756,  527,  522,  738,  202,  608,  112,  664,  532,  615,  660,  626,  280,   78,  296,  459,  359,  386,  797,  453,  170,  233,  152,  223,  537,  261,  404,  274,  175,  288,  501,  286,  335,  111,  534,  488,  257,  697,  662,  388,  631,   96,  475,  303,  564,  758,  622,  632,  621,  612,  236,  225,  451,  612,  252,  211,  402,  207,  940,  627,  142,  465,  250,  580,  542,  492,  540,  530,  315,  723,  387,  176,  716,  387,  445,  421,  348,  308,  478,  516,  324,   92,  172,  678,  403,  455,  424,  607,  920,  632,  864,  547,  333,    0,  642,  627,   94],
        [  489,    0,  184,  784,  972,  569,  518,  704,  823,  711,  290,  608,  257,  653,  457,  665,  352, 1003,  459,  709,  336,  539,  957,  289,  969,  123,  655,  904,  569,  772,  284,  944,  305,  426,  297,  544,  781,  638,  772,  371,  416,  452,  859,  801,  924,  174,  807,  401,  738,  211,  864,  667,   87,  483,  910,  457,  612,  580,  915,  178,  279,  238,  247, 1027,  272,  417,  854,  459,   37,  651,  781,  442,  445,  582,  587,  541,  774,  572,   95,  771,  727,  423,  664,  954,  162,  273,  472,  285,  666,  911,  869,  901,  402,  172,  128,  878,  662,  527,  240,  262,  924,  916,   68,  625,  752,  511,  654,  355,  642,    0,  632,  644],
        [  334,    0,  528,  284,  508,  139,  221,  655,  234,  144,  874,  157,  739,  786,  175,  137,  283,  573,  279,  494,  308,  619,  385,  795,  437,  743,   27,  711,  617,  467,  378,  667,  417,  377,  735,  698,  545,  490,  545,  860,  445,  824,  620,  658,  850,  485,  523,  365,  635,  425,  396,  848,  605,  186,  565,  193,  689,  153,  904,  726,  476,  814,  404,  519,  371,  606,  816,  219,  635,  403,  837,  815,  504,  431,   51,  666,  304,  789,  541,  230,  227,  210,  129,  855,  556,  620,  598,  427,  279,  505,  468,  598,  693,  522,  595,  588,  559,  467,  843,  629,  515,  536,  565,  370,  139,  385,  104,  664,  627,  632,    0,  546],
        [  242,    0,  460,  405,  454,  409,  339,  110,  529,  472,  704,  673,  534,  278,  493,  678,  478,  446,  680,  114,  562,  166,  572,  575,  525,  678,  543,  261,  138,  209,  427,  311,  361,  747,  494,  245,  162,   59,  151,  592,  235,  471,  223,  161,  326,  488,  209,  291,  106,  508,  397,  350,  689,  598,  316,  569,  185,  393,  363,  591,  725,  657,  598,  536,  574,  270,  278,  386,  617,  159,  295,  467,  200,  882,  550,  212,  372,  334,  571,  449,  400,  480,  443,  344,  705,  411,  213,  680,  296,  364,  336,  285,  359,  474,  523,  260,   19,  125,  712,  427,  374,  347,  601,  856,  542,  808,  461,  373,   94,  644,  546,    0]
    ]
}
